README.txt
setup.cfg
setup.py
sqlautocode/__init__.py
sqlautocode/config.py
sqlautocode/constants.py
sqlautocode/declarative.py
sqlautocode/formatter.py
sqlautocode/loader.py
sqlautocode/main.py
sqlautocode/model.py
sqlautocode/util.py
sqlautocode.egg-info/PKG-INFO
sqlautocode.egg-info/SOURCES.txt
sqlautocode.egg-info/dependency_links.txt
sqlautocode.egg-info/entry_points.txt
sqlautocode.egg-info/requires.txt
sqlautocode.egg-info/top_level.txt
sqlautocode.egg-info/zip-safe
sqlautocode/tests/__init__.py
sqlautocode/tests/base.py
sqlautocode/tests/test_declarative.py